almanachclient/__init__.py
almanachclient/exceptions.py
almanachclient/http_client.py
almanachclient/keystone_client.py
almanachclient/shell.py
almanachclient/version.py
almanachclient/commands/__init__.py
almanachclient/commands/attach_volume.py
almanachclient/commands/create_instance.py
almanachclient/commands/create_volume.py
almanachclient/commands/create_volume_type.py
almanachclient/commands/delete_instance.py
almanachclient/commands/delete_volume.py
almanachclient/commands/delete_volume_type.py
almanachclient/commands/detach_volume.py
almanachclient/commands/endpoint.py
almanachclient/commands/get_entity.py
almanachclient/commands/get_volume_type.py
almanachclient/commands/list_entity.py
almanachclient/commands/list_instance.py
almanachclient/commands/list_volume_type.py
almanachclient/commands/list_volumes.py
almanachclient/commands/resize_instance.py
almanachclient/commands/resize_volume.py
almanachclient/commands/update_instance_entity.py
almanachclient/commands/version.py
almanachclient/tests/__init__.py
almanachclient/tests/base.py
almanachclient/tests/test_keystone_client.py
almanachclient/tests/commands/__init__.py
almanachclient/tests/commands/test_attach_volume.py
almanachclient/tests/commands/test_create_instance.py
almanachclient/tests/commands/test_create_volume.py
almanachclient/tests/commands/test_create_volume_type.py
almanachclient/tests/commands/test_delete_instance.py
almanachclient/tests/commands/test_delete_volume.py
almanachclient/tests/commands/test_delete_volume_type.py
almanachclient/tests/commands/test_detach_volume.py
almanachclient/tests/commands/test_get_entity.py
almanachclient/tests/commands/test_get_volume_type.py
almanachclient/tests/commands/test_list_entity.py
almanachclient/tests/commands/test_list_instance.py
almanachclient/tests/commands/test_list_volume.py
almanachclient/tests/commands/test_list_volume_type.py
almanachclient/tests/commands/test_resize_instance.py
python_almanachclient-0.0.6.dist-info/DESCRIPTION.rst
python_almanachclient-0.0.6.dist-info/METADATA
python_almanachclient-0.0.6.dist-info/RECORD
python_almanachclient-0.0.6.dist-info/WHEEL
python_almanachclient-0.0.6.dist-info/entry_points.txt
python_almanachclient-0.0.6.dist-info/metadata.json
python_almanachclient-0.0.6.dist-info/pbr.json
python_almanachclient-0.0.6.dist-info/top_level.txt
